prefect_kubernetes/__init__.py
prefect_kubernetes/_logging.py
prefect_kubernetes/_version.py
prefect_kubernetes/credentials.py
prefect_kubernetes/custom_objects.py
prefect_kubernetes/deployments.py
prefect_kubernetes/exceptions.py
prefect_kubernetes/flows.py
prefect_kubernetes/jobs.py
prefect_kubernetes/observer.py
prefect_kubernetes/pods.py
prefect_kubernetes/services.py
prefect_kubernetes/settings.py
prefect_kubernetes/utilities.py
prefect_kubernetes/worker.py
prefect_kubernetes/experimental/__init__.py
prefect_kubernetes/experimental/decorators.py
prefect_kubernetes-0.7.2.dist-info/licenses/LICENSE
prefect_kubernetes-0.7.2.dist-info/METADATA
prefect_kubernetes-0.7.2.dist-info/WHEEL
prefect_kubernetes-0.7.2.dist-info/entry_points.txt
prefect_kubernetes-0.7.2.dist-info/top_level.txt
prefect_kubernetes-0.7.2.dist-info/RECORD
